bffacilities/__init__.py
bffacilities/__main__.py
bffacilities/_constants.py
bffacilities/_frame.py
bffacilities/_globals.py
bffacilities/_plugin.py
bffacilities/bluetooth.py
bffacilities/dbmodel.py
bffacilities/mathutils.py
bffacilities/socketserver.py
bffacilities/utils.py
bffacilities/win_tray.py
bffacilities/flask/__init__.py
bffacilities/flask/api_server.py
bffacilities/flask/db_websession.py
bffacilities/flask/mail.py
bffacilities/flask/utils.py
bffacilities/flask/websession.py
bffacilities/imgs/logo.ico
bffacilities/locale/gitrepo.pot
bffacilities/locale/monitor.pot
bffacilities/locale/en_US/LC_MESSAGES/gitrepo.mo
bffacilities/locale/en_US/LC_MESSAGES/gitrepo.po
bffacilities/locale/zh_CN/LC_MESSAGES/gitrepo.mo
bffacilities/locale/zh_CN/LC_MESSAGES/gitrepo.po
bffacilities/locale/zh_CN/LC_MESSAGES/monitor.mo
bffacilities/locale/zh_CN/LC_MESSAGES/monitor.po
bffacilities/myscripts/broadcast.py
bffacilities/myscripts/checkGitRepo.py
bffacilities/myscripts/generateDebPacket.py
bffacilities/myscripts/generateMultiCpack.py
bffacilities/myscripts/generateQtTest.py
bffacilities/myscripts/gitkey.py
bffacilities/myscripts/gitrepo.py
bffacilities/myscripts/meta.json
bffacilities/myscripts/monitor.py
bffacilities/myscripts/paperUtil.py
bffacilities/myscripts/pigpio.py
bffacilities/myscripts/qtStatement.py
bffacilities/myscripts/splitimage.py
bffacilities/myscripts/wakeonlan.py
bffacilities/network/__init__.py
bffacilities/network/bluetooth.py
bffacilities/network/servers.py
bffacilities/network/sock.py
bffacilities/network/socketserver_select.py
bffacilities/other/systemd/tightvncserver@.service
bffacilities/other/systemd/x11vnc.service
bffacilities/other/winbat/createshortcut.bat
bffacilities/other/winbat/createshortcut.js
bffacilities/other/winbat/test.js
bffacilities/template/generateQtTest.jinja2
bffacilities/template/generateQtTestCmake.jinja2
bffacilities/torch/__init__.py
bffacilities/torch/datasets.py
bffacilities/torch/featureutil.py
bffacilities-0.1.0.dist-info/LICENSE
bffacilities-0.1.0.dist-info/METADATA
bffacilities-0.1.0.dist-info/WHEEL
bffacilities-0.1.0.dist-info/entry_points.txt
bffacilities-0.1.0.dist-info/top_level.txt
bffacilities-0.1.0.dist-info/RECORD
